README.md
setup.cfg
setup.py
dbpedia/__init__.py
dbpedia/api_client.py
dbpedia/configuration.py
dbpedia/exceptions.py
dbpedia/rest.py
dbpedia/api/__init__.py
dbpedia/api/abbey_api.py
dbpedia/api/academic_journal_api.py
dbpedia/api/activity_api.py
dbpedia/api/actor_api.py
dbpedia/api/administrative_region_api.py
dbpedia/api/adult_actor_api.py
dbpedia/api/agent_api.py
dbpedia/api/agglomeration_api.py
dbpedia/api/aircraft_api.py
dbpedia/api/airline_api.py
dbpedia/api/airport_api.py
dbpedia/api/album_api.py
dbpedia/api/algerian_settlement_api.py
dbpedia/api/altitude_api.py
dbpedia/api/amateur_boxer_api.py
dbpedia/api/ambassador_api.py
dbpedia/api/american_football_coach_api.py
dbpedia/api/american_football_league_api.py
dbpedia/api/american_football_player_api.py
dbpedia/api/american_football_team_api.py
dbpedia/api/amphibian_api.py
dbpedia/api/amusement_park_attraction_api.py
dbpedia/api/anatomical_structure_api.py
dbpedia/api/animal_api.py
dbpedia/api/animanga_character_api.py
dbpedia/api/anime_api.py
dbpedia/api/annotation_api.py
dbpedia/api/arachnid_api.py
dbpedia/api/archaea_api.py
dbpedia/api/archeologist_api.py
dbpedia/api/archipelago_api.py
dbpedia/api/architect_api.py
dbpedia/api/architectural_structure_api.py
dbpedia/api/archive_api.py
dbpedia/api/area_api.py
dbpedia/api/arena_api.py
dbpedia/api/aristocrat_api.py
dbpedia/api/artery_api.py
dbpedia/api/artificial_satellite_api.py
dbpedia/api/artist_api.py
dbpedia/api/artist_discography_api.py
dbpedia/api/artwork_api.py
dbpedia/api/asteroid_api.py
dbpedia/api/astronaut_api.py
dbpedia/api/athlete_api.py
dbpedia/api/athletics_api.py
dbpedia/api/athletics_player_api.py
dbpedia/api/atoll_api.py
dbpedia/api/australian_football_league_api.py
dbpedia/api/australian_football_team_api.py
dbpedia/api/australian_rules_football_player_api.py
dbpedia/api/austrian_administrative_region_api.py
dbpedia/api/austrian_settlement_api.py
dbpedia/api/auto_racing_league_api.py
dbpedia/api/automobile_api.py
dbpedia_api.egg-info/PKG-INFO
dbpedia_api.egg-info/SOURCES.txt
dbpedia_api.egg-info/dependency_links.txt
dbpedia_api.egg-info/requires.txt
dbpedia_api.egg-info/top_level.txt
