Metadata-Version: 1.0
Name: dbpedia-api
Version: 0.0.1
Summary: DBpedia
Home-page: https://pypi.org/project/dbpedia-api/
Author: OpenAPI Generator community
Author-email: team@openapitools.org
License: UNKNOWN
Keywords: OpenAPI,OpenAPI-Generator,DBpedia
Platform: UNKNOWN
